sql_ingest_configs/__init__.py
sql_ingest_configs_dp/__init__.py
sql_ingest_configs_dp-0.1.dist-info/LICENSE.txt
sql_ingest_configs_dp-0.1.dist-info/METADATA
sql_ingest_configs_dp-0.1.dist-info/WHEEL
sql_ingest_configs_dp-0.1.dist-info/top_level.txt
sql_ingest_configs_dp-0.1.dist-info/RECORD
